gfmrag/__init__.py
gfmrag/datasets/__init__.py
gfmrag/datasets/kg_dataset.py
gfmrag/datasets/qa_dataset.py
gfmrag/doc_rankers.py
gfmrag/evaluation/__init__.py
gfmrag/evaluation/base_evaluator.py
gfmrag/evaluation/hotpot_qa_evaluator.py
gfmrag/evaluation/musique_evaluator.py
gfmrag/evaluation/retrieval_evaluator.py
gfmrag/evaluation/two_wiki_qa_evaluator.py
gfmrag/gfmrag_retriever.py
gfmrag/kg_construction/__init__.py
gfmrag/kg_construction/entity_linking_model/__init__.py
gfmrag/kg_construction/entity_linking_model/base_model.py
gfmrag/kg_construction/entity_linking_model/colbert_el_model.py
gfmrag/kg_construction/entity_linking_model/dpr_el_model.py
gfmrag/kg_construction/kg_constructor.py
gfmrag/kg_construction/langchain_util.py
gfmrag/kg_construction/ner_model/__init__.py
gfmrag/kg_construction/ner_model/base_model.py
gfmrag/kg_construction/ner_model/llm_ner_model.py
gfmrag/kg_construction/openie_extraction_instructions.py
gfmrag/kg_construction/openie_model/__init__.py
gfmrag/kg_construction/openie_model/base_model.py
gfmrag/kg_construction/openie_model/llm_openie_model.py
gfmrag/kg_construction/qa_constructor.py
gfmrag/kg_construction/utils.py
gfmrag/kg_indexer.py
gfmrag/llms/__init__.py
gfmrag/llms/base_hf_causal_model.py
gfmrag/llms/base_language_model.py
gfmrag/llms/chatgpt.py
gfmrag/losses.py
gfmrag/models.py
gfmrag/prompt_builder.py
gfmrag/text_emb_models/__init__.py
gfmrag/text_emb_models/base_model.py
gfmrag/text_emb_models/nv_embed.py
gfmrag/ultra/__init__.py
gfmrag/ultra/base_nbfnet.py
gfmrag/ultra/layers.py
gfmrag/ultra/models.py
gfmrag/ultra/query_utils.py
gfmrag/ultra/rspmm/__init__.py
gfmrag/ultra/rspmm/rspmm.py
gfmrag/ultra/rspmm/source/operator.cuh
gfmrag/ultra/rspmm/source/rspmm.cpp
gfmrag/ultra/rspmm/source/rspmm.cu
gfmrag/ultra/rspmm/source/rspmm.h
gfmrag/ultra/rspmm/source/util.cuh
gfmrag/ultra/tasks.py
gfmrag/ultra/util.py
gfmrag/ultra/variadic.py
gfmrag/utils/__init__.py
gfmrag/utils/dataloader.py
gfmrag/utils/qa_utils.py
gfmrag-0.2.2.dist-info/LICENSE
gfmrag-0.2.2.dist-info/METADATA
gfmrag-0.2.2.dist-info/WHEEL
gfmrag-0.2.2.dist-info/RECORD
