Metadata-Version: 2.3
Name: gfmrag
Version: 0.2.2
Summary: Graph Foundation Model for Retrieval Augmented Generation
Author: Linhao Luo
Author-email: linhao.luo@monash.edu
Requires-Python: >=3.12,<3.13
Classifier: Programming Language :: Python :: 3
Classifier: Programming Language :: Python :: 3.12
Requires-Dist: easydict (>=1.13,<2.0)
Requires-Dist: faiss-gpu-cu12 (>=1.9.0.post1,<2.0.0)
Requires-Dist: hydra-core (>=1.3.2,<2.0.0)
Requires-Dist: langchain (>=0.3.9,<0.4.0)
Requires-Dist: langchain-community (>=0.3.9,<0.4.0)
Requires-Dist: langchain-nvidia-ai-endpoints (>=0.3.9,<0.4.0)
Requires-Dist: langchain-openai (>=0.2.11,<0.3.0)
Requires-Dist: langchain-together (>=0.2.0,<0.3.0)
Requires-Dist: ninja (>=1.11.1.1,<2.0.0.0)
Requires-Dist: openai (>=1.52.2,<2.0.0)
Requires-Dist: python-dotenv (>=1.0.1,<2.0.0)
Requires-Dist: pyyaml (>=6.0.2,<7.0.0)
Requires-Dist: ragatouille (>=0.0.9.post2,<0.0.10)
Requires-Dist: sentence-transformers (>=3.2.0)
Requires-Dist: tiktoken (>=0.8.0,<0.9.0)
Requires-Dist: torch (>=2.4.1)
Requires-Dist: torch-geometric (>=2.4.0,<3.0.0)
Requires-Dist: tqdm (>=4.66.5,<5.0.0)
Requires-Dist: transformers (>=4.46.1,<5.0.0)
Requires-Dist: wandb (>=0.18.5,<0.19.0)
